DiscordEXT/__init__.py
DiscordEXT/users/__init__.py
DiscordEXT/users/activity.py
DiscordEXT/users/bot.py
DiscordEXT/users/info.py
DiscordEXT/users/message.py
DiscordEXT/users/status.py
discordext-0.1.2.dist-info/METADATA
discordext-0.1.2.dist-info/WHEEL
discordext-0.1.2.dist-info/top_level.txt
discordext-0.1.2.dist-info/RECORD
